blob_path/__init__.py
blob_path/copy.py
blob_path/deserialise.py
blob_path/implicit.py
blob_path/shortcuts.py
blob_path/tmpdir.py
blob_path/backends/__init__.py
blob_path/backends/azure_blob_storage.py
blob_path/backends/local_relative.py
blob_path/backends/s3.py
blob_path/core/__init__.py
blob_path/core/interface.py
blob_path/core/open_.py
blob_path/core/presigned.py
blob_path-0.1.2.dist-info/METADATA
blob_path-0.1.2.dist-info/WHEEL
blob_path-0.1.2.dist-info/licenses/LICENSE
blob_path-0.1.2.dist-info/RECORD
