Metadata-Version: 2.4
Name: blob-path
Version: 0.1.2
Summary: A pathlib-like cloud agnostic object storage library
Author-email: Hariom Narang <hariom.2711@gmail.com>
License-File: LICENSE
Requires-Python: >=3.12
Requires-Dist: pydantic>=2.10.1
Requires-Dist: typing-extensions>=4.12.2
Provides-Extra: aws
Requires-Dist: boto3>=1.35.68; extra == 'aws'
Provides-Extra: azure
Requires-Dist: azure-identity>=1.19.0; extra == 'azure'
Requires-Dist: azure-storage-blob>=12.24.0; extra == 'azure'
Provides-Extra: gcp
Requires-Dist: google-cloud-storage>=2.18.2; extra == 'gcp'
